namespace/__init__.py
namespace-0.1.3.dist-info/LICENSE
namespace-0.1.3.dist-info/WHEEL
namespace-0.1.3.dist-info/METADATA
namespace-0.1.3.dist-info/RECORD
